yaasr/__init__.py
yaasr/exceptions.py
yaasr/processors/__init__.py
yaasr/processors/archive/__init__.py
yaasr/processors/archive/google_cloud.py
yaasr/processors/archive/s3.py
yaasr/processors/archive/ssh.py
yaasr/processors/audio/__init__.py
yaasr/processors/audio/reduce.py
yaasr/recorder/__init__.py
yaasr/recorder/stream.py
yaasr/streams/am630-jujuy/data.json
yaasr/streams/fm1023-universidad-cordoba/data.json
yaasr/streams/la-arena-noticias-995-la-pampa/data.json
yaasr/streams/lu5-neuquen/data.json
yaasr/streams/radio-bio-bio-santiago-chile/data.json
yaasr/streams/radio-congo-argentina/data.json
yaasr/streams/radio-universidad-cordoba-argentina/data.json
yaasr/streams/radio2-rosario/data.json
yaasr/streams/rne-radio-nacional-madrid/data.json
yaasr/terminal/__init__.py
yaasr/terminal/supervisor.py
yaasr/terminal/tpl/supervisor.ini
yaasr-0.4.13.dist-info/LICENSE
yaasr-0.4.13.dist-info/METADATA
yaasr-0.4.13.dist-info/WHEEL
yaasr-0.4.13.dist-info/entry_points.txt
yaasr-0.4.13.dist-info/top_level.txt
yaasr-0.4.13.dist-info/RECORD
