Metadata-Version: 2.1
Name: yaasr
Version: 0.4.13
Summary: Yet another audio stream recorder
Home-page: https://github.com/avdata99/yaasr
Author: Andres Vazquez
Author-email: andres@data99.com.ar
License: UNKNOWN
Platform: UNKNOWN
Classifier: Programming Language :: Python :: 3
Classifier: License :: OSI Approved :: GNU General Public License v3 or later (GPLv3+)
Classifier: Operating System :: OS Independent
Classifier: Development Status :: 4 - Beta
Classifier: Intended Audience :: Developers
Requires-Python: >=3.6
Requires-Dist: requests (>=2.25.1)
Requires-Dist: pydub (>=0.24.1)
Requires-Dist: paramiko (>=2.7.2)
Requires-Dist: google-cloud-storage (>=1.36.0)
Requires-Dist: jinja2 (>=2.11.3)
